openvpn_helpers/__init__.py
openvpn_helpers/inline_helper.py
openvpn_helpers-0.1.6.dist-info/LICENSE
openvpn_helpers-0.1.6.dist-info/METADATA
openvpn_helpers-0.1.6.dist-info/WHEEL
openvpn_helpers-0.1.6.dist-info/entry_points.txt
openvpn_helpers-0.1.6.dist-info/RECORD
